[{"id":1,"title":"Producto del Challenge","price":2000,"created_at":"2022-12-13 10:41"},{"id":2,"title":"Producto del Challenge2","price":2002,"created_at":"2022-12-13 10:41"},{"id":3,"title":"Producto del Challenge3","price":2000,"created_at":"2022-12-13 10:41"},{"id":4,"title":"Producto del Challenge4","price":2002,"created_at":"2022-12-13 10:41"},{"id":5,"title":"Producto del Challenge5","price":2000,"created_at":"2022-12-13 10:41"},{"id":6,"title":"Producto del Challenge6","price":2002,"created_at":"2022-12-13 10:41"},{"id":7,"title":"Producto del Challenge7","price":2000,"created_at":"2022-12-13 10:41"},{"id":8,"title":"Producto del Challenge8","price":2002,"created_at":"2022-12-13 10:41"},{"id":9,"title":"sdfgdsg","price":"1432243","created_at":"2024-06-27 22:50:59"},{"id":10,"title":"sdfgdsgijom","price":"1432243","created_at":"2024-06-27 23:19:19"},{"id":11,"title":"gdsgijom","price":"1432243","created_at":"2024-06-27 23:19:23"},{"id":12,"title":"gdsgijomfgdhfdg","price":"1432243","created_at":"2024-06-27 23:19:27"},{"id":13,"title":"nose","price":"42","created_at":"2024-06-28 14:48:58"},{"id":14,"title":"dfgh","price":"4563","created_at":"2024-06-28 15:14:32"},{"id":15,"title":"dsafgdsa","price":"651","created_at":"2024-06-28 15:20:42"},{"id":16,"title":"sdafe","price":"6541","created_at":"2024-06-28 15:22:22"},{"id":17,"title":"saedfes","price":"543","created_at":"2024-06-28 15:22:46"},{"id":18,"title":"sfdf","price":"2131653","created_at":"2024-06-28 15:26:21"},{"id":19,"title":"sdaf","price":"6541","created_at":"2024-06-28 15:27:55"},{"id":20,"title":"saf","price":"58964","created_at":"2024-06-28 15:29:52"},{"id":21,"title":"jjjjjj","price":"56156","created_at":"2024-06-28 16:05:16"},{"id":22,"title":"dfg","price":"3521","created_at":"2024-06-28 16:07:08"},{"id":23,"title":"fdh","price":"5641","created_at":"2024-06-28 16:10:39"},{"id":24,"title":"esrgse","price":"561468","created_at":"2024-06-28 16:11:35"},{"id":25,"title":"rdghredh","price":"12869512","created_at":"2024-06-28 16:12:40"},{"id":26,"title":"erh","price":"561","created_at":"2024-06-28 16:13:43"},{"id":27,"title":"dfsg","price":"34324","created_at":"2024-06-28 22:05:01"}]